openadapt_tray/__init__.py
openadapt_tray/__main__.py
openadapt_tray/app.py
openadapt_tray/config.py
openadapt_tray/icons.py
openadapt_tray/ipc.py
openadapt_tray/menu.py
openadapt_tray/notifications.py
openadapt_tray/shortcuts.py
openadapt_tray/state.py
openadapt_tray/platform/__init__.py
openadapt_tray/platform/base.py
openadapt_tray/platform/linux.py
openadapt_tray/platform/macos.py
openadapt_tray/platform/windows.py
openadapt_tray-0.0.1.dist-info/METADATA
openadapt_tray-0.0.1.dist-info/WHEEL
openadapt_tray-0.0.1.dist-info/entry_points.txt
openadapt_tray-0.0.1.dist-info/RECORD
