Metadata-Version: 2.4
Name: openadapt-tray
Version: 0.0.1
Summary: System tray application for OpenAdapt
Project-URL: Homepage, https://openadapt.ai
Project-URL: Documentation, https://docs.openadapt.ai
Project-URL: Repository, https://github.com/OpenAdaptAI/openadapt-tray
Author-email: "MLDSAI Inc." <richard@mldsai.com>
License-Expression: MIT
Keywords: gui,menu-bar,openadapt,system-tray
Classifier: Development Status :: 3 - Alpha
Classifier: Intended Audience :: Developers
Classifier: License :: OSI Approved :: MIT License
Classifier: Operating System :: MacOS
Classifier: Operating System :: Microsoft :: Windows
Classifier: Operating System :: POSIX :: Linux
Classifier: Programming Language :: Python :: 3
Classifier: Programming Language :: Python :: 3.10
Classifier: Programming Language :: Python :: 3.11
Classifier: Programming Language :: Python :: 3.12
Requires-Python: >=3.10
Requires-Dist: click>=8.0.0
Requires-Dist: desktop-notifier>=6.2.0
Requires-Dist: pillow>=9.0.0
Requires-Dist: pynput>=1.7.0
Requires-Dist: pystray>=0.19.0
Provides-Extra: all
Requires-Dist: pyobjc-framework-cocoa>=9.0; extra == 'all'
Requires-Dist: rumps>=0.4.0; extra == 'all'
Provides-Extra: dev
Requires-Dist: pytest-mock>=3.10.0; extra == 'dev'
Requires-Dist: pytest>=8.0.0; extra == 'dev'
Requires-Dist: ruff>=0.1.0; extra == 'dev'
Provides-Extra: macos-native
Requires-Dist: pyobjc-framework-cocoa>=9.0; extra == 'macos-native'
Requires-Dist: rumps>=0.4.0; extra == 'macos-native'
